{
  "GlobalConfiguration": {
    "BaseUrl": "http://localhost:8800"
  },
  "ReRoutes": [
    // API:TestMicroService
    {
      "DownstreamPathTemplate": "/api/{url}",
      "DownstreamScheme": "http",
      "DownstreamHostAndPorts": [
        {
          "Host": "localhost",
          "Port": "8810"
        }
      ],
      "UpstreamPathTemplate": "/TestService/{url}",
      "UpstreamHttpMethod": [ "GET", "POST", "PUT", "DELETE" ]
    },
    // API:CAS.ProductService
    {
      "DownstreamPathTemplate": "/api/{url}",
      "DownstreamScheme": "http",
      "DownstreamHostAndPorts": [
        {
          "Host": "localhost",
          "Port": "8820"
        }
      ],
      "UpstreamPathTemplate": "/ProductService/{url}",
      "UpstreamHttpMethod": [ "GET", "POST", "PUT", "DELETE" ]
    }
  ]
}